{
  "data_source": [
    {
      "name": "ai4sh_fi-jokioinen",
      "site": [
        {
          "name": "fi-jokioinen",
          "point": [
            {
              "name": "14-r",
              "latitude": 60.815504247,
              "longitude": 23.505183157,
              "setting": "uniform",
              "sampling_log": [
                {
                  "name": "fi-jokioinen-20241008",
                  "date_stamp": "20241008",
                  "person__email": "thomasg@xspectre.com",
                  "sample": [
                    {
                      "name": "fi-jokioinen-20241008_14-r_0-20",
                      "min_depth": 0,
                      "max_depth": 20,
                      "observation": [
                        {
                          "sample_preparation__name": "mixed-untreated-soil-in-lab",
                          "person__email": "thomasg@xspectre.com",
                          "subsample": "d",
                          "replicate": 0,
                          "n_repeats": 6,
                          "date_stamp": "20241011",
                          "logistic": {
                            "sample_preservation__name": null,
                            "sample_transport__name": null,
                            "transport_duration_h": 0,
                            "sample_storage__name": null,
                            "storage_duration_h": 72,
                            "person__email": "thomasg@xspectre.com"
                          },
                          "analysis_method": {
                            "xspectre-ise-ph-liquid": [
                              {
                                "value": 6.26,
                                "standard_deviation": 0.0,
                                "unit__name": "pH",
                                "indicator__name": "xspectre-ise-ph-liquid_ph(water)",
                                "analysis_method__name": "ise-ph-5xh20",
                                "instrument_brand__name": "ise-liquid",
                                "instrument_model__name": "tf38415",
                                "instrument_id": "0"
                              }
                            ]
                          }
                        }
                      ]
                    }
                  ]
                }
              ]
            }
          ]
        }
      ]
    }
  ]
}