{
  "data_source": [
    {
      "name": "ai4sh_se-loennstorp",
      "site": [
        {
          "name": "se-loennstorp",
          "point": [
            {
              "name": "3-organic",
              "latitude": 55.6503416666666,
              "longitude": 13.0796972222222,
              "setting": "uniform",
              "sampling_log": [
                {
                  "name": "se-loennstorp-20240815",
                  "date_stamp": "20240815",
                  "person__email": "sampling@gmail.com",
                  "sample": [
                    {
                      "name": "se-loennstorp-20240815_3-organic_20-50",
                      "min_depth": 20,
                      "max_depth": 50,
                      "observation": [
                        {
                          "sample_preparation__name": "dried-sieved-soil-in-lab",
                          "person__email": "analysis@gmail.com",
                          "subsample": "a",
                          "replicate": 5,
                          "n_repeats": 3,
                          "date_stamp": "20241107",
                          "logistic": {
                            "sample_preservation__name": null,
                            "sample_transport__name": null,
                            "transport_duration_h": 0,
                            "sample_storage__name": null,
                            "storage_duration_h": 2016,
                            "person__email": "logistic@gmail.com"
                          },
                          "analysis_method": {
                            "neospectra-scan": [
                              {
                                "value": [
                                  0.29875429394925956,
                                  0.2993452473122377,
                                  0.3001061536674847,
                                  0.30094412929260766,
                                  0.30184107452551473,
                                  0.30289992406565025,
                                  0.30429278664226006,
                                  0.3061590258218399,
                                  0.3085575689523304,
                                  0.31143734811805357,
                                  0.3146619279002407,
                                  0.3180717887189809,
                                  0.32155241891035374,
                                  0.32506845160710507,
                                  0.32864398450244253,
                                  0.3323022637024538,
                                  0.33600054367630655,
                                  0.3395908639819538,
                                  0.34283590057689767,
                                  0.3455382241767089,
                                  0.3475972202883856,
                                  0.349057745271737,
                                  0.350096896926115,
                                  0.3509643264342469,
                                  0.3519041169264476,
                                  0.35308858180432373,
                                  0.35458603880801076,
                                  0.35636571706173364,
                                  0.3583365103385196,
                                  0.3603977594298983,
                                  0.36247812977132,
                                  0.3645604591309549,
                                  0.3666667034203966,
                                  0.36882807902760084,
                                  0.371059468010216,
                                  0.3733344699525365,
                                  0.37557860831794154,
                                  0.37766995464891556,
                                  0.3794583534417083,
                                  0.3807972926574085,
                                  0.38158726133582166,
                                  0.38180988240373276,
                                  0.3815954215642738,
                                  0.381219025643968,
                                  0.380981244373721,
                                  0.3811478843017247,
                                  0.38186581813530196,
                                  0.3831210959554049,
                                  0.3847471380671481,
                                  0.3864882628600544,
                                  0.38808896845824625,
                                  0.389375889723939,
                                  0.3903038527948893,
                                  0.3909369855718967,
                                  0.39141729179822105,
                                  0.3918579395581887,
                                  0.39228705746673886,
                                  0.39265979286401853,
                                  0.39289911082161166,
                                  0.3929548484826029,
                                  0.3928408626099821,
                                  0.39263541055650214,
                                  0.3924424872614645,
                                  0.3923318506869805,
                                  0.39230097140607123,
                                  0.3922584331688833,
                                  0.39207346688791467,
                                  0.39165958849281596,
                                  0.3910115742521668,
                                  0.3902100658650294,
                                  0.38937971426813806,
                                  0.38862409026465045,
                                  0.3879697784735007,
                                  0.38734612941304697,
                                  0.38661515519458595,
                                  0.3856331052576742,
                                  0.38431550372738327,
                                  0.3826621331062687,
                                  0.3808012882702279,
                                  0.3788560337690347,
                                  0.37691023286734526,
                                  0.3749761352645519,
                                  0.3730034318600632,
                                  0.3709263332198216,
                                  0.36871538609879795,
                                  0.36640867353272566,
                                  0.3640969305499456,
                                  0.3618749498710507,
                                  0.3597825892582881,
                                  0.35775608937526654,
                                  0.35567812243915076,
                                  0.3534952659440807,
                                  0.3513189760868375,
                                  0.3494918601923382,
                                  0.3485626754699112,
                                  0.3491601686348053,
                                  0.3517840822367345,
                                  0.3565935687937033,
                                  0.36328296105054625,
                                  0.37111986530919316,
                                  0.3790806075064536,
                                  0.3861905963351839,
                                  0.39184276608253904,
                                  0.3958143874747232,
                                  0.3982349402336972,
                                  0.39947494612336665,
                                  0.39998944636761374,
                                  0.40017052643589923,
                                  0.40025801414648576,
                                  0.4003178132631977,
                                  0.40029414917041434,
                                  0.4000813544745935,
                                  0.39962334956510637,
                                  0.39895491491064944,
                                  0.3981640077891161,
                                  0.3973537306298301,
                                  0.3966002040606266,
                                  0.3959281822000046,
                                  0.3953157297221669,
                                  0.3947202260438177,
                                  0.39410204914954133,
                                  0.39344129058624505,
                                  0.39273736011043864,
                                  0.39199933609697424,
                                  0.39123292625450307,
                                  0.39043882350558534,
                                  0.3896211297265175,
                                  0.3887986908587753,
                                  0.3880044848053304,
                                  0.3872739463952554,
                                  0.3866247946486534,
                                  0.3860374084512831,
                                  0.3854522103171662,
                                  0.38478554334652076,
                                  0.3839555907932803,
                                  0.38295714529665614,
                                  0.3818492184260188,
                                  0.38074246172317283,
                                  0.37975847993879436,
                                  0.3789842117507041,
                                  0.3784313250588703,
                                  0.37803335261553,
                                  0.3776645730961801,
                                  0.3771851064663817,
                                  0.3764889146517104,
                                  0.3755269195648134,
                                  0.374357406190055,
                                  0.37307627200257265,
                                  0.3717811647734229,
                                  0.3705427712574235,
                                  0.3693891051640677,
                                  0.36830833115070627,
                                  0.36726548711880974,
                                  0.36622392407469634,
                                  0.365162964576226,
                                  0.36408526846705763,
                                  0.3630206460908372,
                                  0.3620085366840531,
                                  0.36108298168426417,
                                  0.3602596165257843,
                                  0.3595308174203867,
                                  0.35886115556100584,
                                  0.3581991626565308,
                                  0.3574885665056557,
                                  0.35668709755337047,
                                  0.35578231303229024,
                                  0.3547943093110367,
                                  0.35377493929251796,
                                  0.3527862665012174,
                                  0.35187095733634643,
                                  0.3510460194688207,
                                  0.3503020782697043,
                                  0.3496148124709551,
                                  0.3489586908537644,
                                  0.34831819023202243,
                                  0.347688468374731,
                                  0.34706903238353104,
                                  0.34645143771199527,
                                  0.34581061663187695,
                                  0.3451130530144841,
                                  0.34433570560380855,
                                  0.3434770698868099,
                                  0.34256715650253744,
                                  0.3416566177930073,
                                  0.34079714936754724,
                                  0.34001965604908163,
                                  0.3393185832265275,
                                  0.3386564036814772,
                                  0.33797990767200664,
                                  0.33724451211859136,
                                  0.3364476521671385,
                                  0.33561842053453683,
                                  0.33480069084484326,
                                  0.3340273172692956,
                                  0.3332997209016639,
                                  0.3325833652756063,
                                  0.3318211577236834,
                                  0.33095630505105744,
                                  0.3299622054419893,
                                  0.32885550049718837,
                                  0.32770457549070153,
                                  0.3266045196537901,
                                  0.3256381455285947,
                                  0.3248570136244794,
                                  0.32426196989163375,
                                  0.32379776115617953,
                                  0.32336532114239863,
                                  0.32284625020613467,
                                  0.3221426921794166,
                                  0.32121067943369985,
                                  0.32008335111833547,
                                  0.31889304921099704,
                                  0.31780107424249127,
                                  0.31693536850344023,
                                  0.3163379195209088,
                                  0.31593489586142326,
                                  0.31556354044254353,
                                  0.31503733240226933,
                                  0.3142353476875033,
                                  0.3131672899146842,
                                  0.31198852668772437,
                                  0.3109666973806401,
                                  0.3103042005321048,
                                  0.3100474548476329,
                                  0.31005993488198597,
                                  0.3100800547419321,
                                  0.3098412251581768,
                                  0.3092012318106683,
                                  0.30821609029984554,
                                  0.3071282187155318,
                                  0.3062559880588943,
                                  0.30586142319820636,
                                  0.305993326716035,
                                  0.3064382869738708,
                                  0.306918699998261,
                                  0.3072161911367041,
                                  0.30727612943117577,
                                  0.3072148234231471,
                                  0.30723199293383174,
                                  0.3074659065687616,
                                  0.3078811917448032,
                                  0.30824278885417794,
                                  0.308172520951786,
                                  0.3074519841679061,
                                  0.3061282062963424,
                                  0.30452252289005144,
                                  0.30309809069350324,
                                  0.3022528737705204,
                                  0.30212369679047724,
                                  0.3025052375902775,
                                  0.3029230745418536,
                                  0.3028320825791312,
                                  0.3018358503310692,
                                  0.29996579763373,
                                  0.2976744686699923,
                                  0.29552792481615664,
                                  0.2940052295182488
                                ],
                                "unit__name": "reflectance",
                                "indicator__name": "spectra",
                                "analysis_method__name": "diffuse spectral spectroscopy",
                                "instrument-brand__name": "neospectra",
                                "instrument-model__name": "proxiscout",
                                "instrument_id": "neoscanner_23040128"
                              }
                            ]
                          }
                        }
                      ]
                    }
                  ]
                }
              ]
            }
          ]
        }
      ]
    }
  ]
}