{
  "data_source": [
    {
      "name": "ai4sh_se-loennstorp",
      "site": [
        {
          "name": "se-loennstorp",
          "point": [
            {
              "name": "79-d",
              "latitude": 55.6663916666666,
              "longitude": 13.1169472222222,
              "setting": "uniform",
              "sampling_log": [
                {
                  "name": "se-loennstorp-20240815",
                  "date_stamp": "20240815",
                  "person__email": "sampling@gmail.com",
                  "sample": [
                    {
                      "name": "se-loennstorp-20240815_79-d_0-20",
                      "min_depth": 0,
                      "max_depth": 20,
                      "observation": [
                        {
                          "sample_preparation__name": "dried-sieved-soil-in-lab",
                          "person__email": "analysis@gmail.com",
                          "subsample": "a",
                          "replicate": 2,
                          "n_repeats": 3,
                          "date_stamp": "20241107",
                          "logistic": {
                            "sample_preservation__name": null,
                            "sample_transport__name": null,
                            "transport_duration_h": 0,
                            "sample_storage__name": null,
                            "storage_duration_h": 2016,
                            "person__email": "logistic@gmail.com"
                          },
                          "analysis_method": {
                            "neospectra-scan": [
                              {
                                "value": [
                                  0.28562032872624965,
                                  0.28682535259615405,
                                  0.28798475893209297,
                                  0.28900898293549293,
                                  0.2899081116809653,
                                  0.29081711104761554,
                                  0.29195282930930583,
                                  0.2935014981422952,
                                  0.29556904267429185,
                                  0.29815107784223455,
                                  0.30114557964097155,
                                  0.30440165238029215,
                                  0.3077796211170509,
                                  0.3111880178166866,
                                  0.3145803218044188,
                                  0.3179170609122866,
                                  0.3211237456713907,
                                  0.32406365588521324,
                                  0.3265707530753276,
                                  0.3285566017608935,
                                  0.3300295781780342,
                                  0.33112242764377536,
                                  0.3320599904521574,
                                  0.33308999462614985,
                                  0.3344059615507306,
                                  0.3360905129311908,
                                  0.3380995829284233,
                                  0.3402900113527182,
                                  0.3424816275911338,
                                  0.3445180905155524,
                                  0.3463225122734247,
                                  0.3479328708148157,
                                  0.34944035205523577,
                                  0.3509536076889384,
                                  0.35255518654789697,
                                  0.35426415933356703,
                                  0.35602084883939333,
                                  0.3576898393566361,
                                  0.3590884203838327,
                                  0.3600320916148486,
                                  0.3603954595361497,
                                  0.360162897069064,
                                  0.3595158770557465,
                                  0.3588219948313279,
                                  0.35849844460927416,
                                  0.35892208403392134,
                                  0.36031091525895476,
                                  0.3626506911515472,
                                  0.36569047881741246,
                                  0.3690167241646495,
                                  0.37217891495072963,
                                  0.3748230888291579,
                                  0.37678584272285365,
                                  0.37809549924234803,
                                  0.37896982476763,
                                  0.3796542693494908,
                                  0.3802886915286346,
                                  0.38089287970931823,
                                  0.3813948426046423,
                                  0.38170732360045484,
                                  0.3818015181287264,
                                  0.3817419762238451,
                                  0.381660650553552,
                                  0.3816866474238573,
                                  0.38187492189562255,
                                  0.38216526220312,
                                  0.3823969084592803,
                                  0.3824264363248185,
                                  0.3822000548978313,
                                  0.38178543140343923,
                                  0.38133749043235865,
                                  0.381014804580752,
                                  0.38088889680862414,
                                  0.3808928084761841,
                                  0.38084179101488613,
                                  0.380515291874867,
                                  0.37976054349308686,
                                  0.3785498089990456,
                                  0.3770616611695231,
                                  0.37548927828260276,
                                  0.37396900169341196,
                                  0.3725107270374119,
                                  0.3710038301243349,
                                  0.36929393770983765,
                                  0.3672878404624136,
                                  0.36502673930573565,
                                  0.3626773881362493,
                                  0.36043888951740577,
                                  0.35840882534010055,
                                  0.35643948655408975,
                                  0.3541849015427466,
                                  0.3512976052785513,
                                  0.34764948757868,
                                  0.34352089409114245,
                                  0.33965192781166686,
                                  0.33710281964886124,
                                  0.33693688093699914,
                                  0.3398294574921424,
                                  0.34576422944743646,
                                  0.3539717916182945,
                                  0.3631165889164961,
                                  0.37165091938825645,
                                  0.37853531603428353,
                                  0.3832999425088102,
                                  0.38604550565233464,
                                  0.38727979775868,
                                  0.38766177322579304,
                                  0.38775254361555006,
                                  0.38786271988440724,
                                  0.3880310729596554,
                                  0.3881247801795744,
                                  0.38797416033644766,
                                  0.3875283086494589,
                                  0.38688730236735014,
                                  0.38620992254843406,
                                  0.38562841415268034,
                                  0.38517863597580343,
                                  0.38479179692030674,
                                  0.38434352263373855,
                                  0.38373179964471094,
                                  0.38293550542094307,
                                  0.3820269510991981,
                                  0.38113509586029815,
                                  0.3803817328447394,
                                  0.37978572922053305,
                                  0.37928368073875374,
                                  0.3787644933475595,
                                  0.3781291984461897,
                                  0.37733813008431805,
                                  0.3764252090571851,
                                  0.37547659947593787,
                                  0.37458316552783977,
                                  0.37379860135882015,
                                  0.37311866892077217,
                                  0.37249574339590824,
                                  0.37186085491639304,
                                  0.3711799847198069,
                                  0.3704541338490632,
                                  0.36970836926159967,
                                  0.3689703079954769,
                                  0.36824882236329837,
                                  0.3675327022022446,
                                  0.36679636647874525,
                                  0.366018356336399,
                                  0.36519092376905576,
                                  0.364321766343247,
                                  0.36342707389712536,
                                  0.3625165287707494,
                                  0.36159012772340576,
                                  0.3606466733228537,
                                  0.35969128725138577,
                                  0.35874135645027644,
                                  0.35782263550758825,
                                  0.3569537500460321,
                                  0.35613444100153624,
                                  0.35534059243011884,
                                  0.3545301163727343,
                                  0.3536654482922669,
                                  0.3527384591865736,
                                  0.3517679042098778,
                                  0.35079338419225203,
                                  0.34985266939879855,
                                  0.3489671318083416,
                                  0.34813213651810776,
                                  0.34732464005549374,
                                  0.346519980809144,
                                  0.3457041579478326,
                                  0.34488464803506874,
                                  0.34407688678364345,
                                  0.34328736862871684,
                                  0.34250644969129174,
                                  0.34170925735790875,
                                  0.3408692486766569,
                                  0.3399746612903437,
                                  0.33903922131250075,
                                  0.338099130185164,
                                  0.3371973917059392,
                                  0.3363660600864431,
                                  0.3356203230555613,
                                  0.3349399768167592,
                                  0.3343003349393172,
                                  0.33368154475936734,
                                  0.33307145119168874,
                                  0.33246064334078235,
                                  0.3318357083469489,
                                  0.33117664357791265,
                                  0.3304620818326704,
                                  0.3296875891205561,
                                  0.328876229831237,
                                  0.3280892358441361,
                                  0.32738419715525746,
                                  0.32678526649373596,
                                  0.32626400204650224,
                                  0.32573981369101235,
                                  0.3251118066136407,
                                  0.3243076129390189,
                                  0.32332091044673283,
                                  0.32222566815152914,
                                  0.3211502509322125,
                                  0.32022399290383263,
                                  0.31951687587951,
                                  0.3189731659929797,
                                  0.31848037122667705,
                                  0.317915171814853,
                                  0.31719939882902093,
                                  0.31633029745238267,
                                  0.31536718070493064,
                                  0.3143880253432532,
                                  0.3134412937467685,
                                  0.312519192601034,
                                  0.3115757040066966,
                                  0.3105743585767041,
                                  0.3095378757341369,
                                  0.30854692302184017,
                                  0.3076991251523529,
                                  0.30703945653831854,
                                  0.30651664068287576,
                                  0.30597654357646525,
                                  0.3052233482946196,
                                  0.3041117586725501,
                                  0.30262658695842437,
                                  0.3009126232968129,
                                  0.2992463788566298,
                                  0.2978555447542172,
                                  0.2968427436509081,
                                  0.29615418117574577,
                                  0.2956205881842642,
                                  0.295059378029503,
                                  0.29437393521919003,
                                  0.29361454692722155,
                                  0.2929545267497203,
                                  0.29262010143239503,
                                  0.2927715706447253,
                                  0.2933804901993178,
                                  0.29430771140439277,
                                  0.2953587956004421,
                                  0.29636831491643434,
                                  0.2972607798171226,
                                  0.29804919167866656,
                                  0.298788042571909,
                                  0.2995049801606666,
                                  0.3001640133545957,
                                  0.30066306195076475,
                                  0.3009161407078277,
                                  0.3008888728341633,
                                  0.30062489343096205,
                                  0.3002161818625034,
                                  0.2997419251559327,
                                  0.29921694543591615,
                                  0.2985698898507183,
                                  0.2977028905330694,
                                  0.29655094879662675,
                                  0.2951394374801417,
                                  0.29361159215916127,
                                  0.29216333172666864,
                                  0.2909639421637812,
                                  0.2901294237815191
                                ],
                                "unit__name": "reflectance",
                                "indicator__name": "spectra",
                                "analysis_method__name": "diffuse spectral spectroscopy",
                                "instrument-brand__name": "neospectra",
                                "instrument-model__name": "proxiscout",
                                "instrument_id": "neoscanner_23040128"
                              }
                            ]
                          }
                        }
                      ]
                    }
                  ]
                }
              ]
            }
          ]
        }
      ]
    }
  ]
}